django_rebel/__init__.py
django_rebel/admin.py
django_rebel/apps.py
django_rebel/exceptions.py
django_rebel/mail_groups.py
django_rebel/mail_templates.py
django_rebel/models.py
django_rebel/paginator.py
django_rebel/services.py
django_rebel/settings.py
django_rebel/tests.py
django_rebel/urls.py
django_rebel/utils.py
django_rebel/views.py
django_rebel/api/__init__.py
django_rebel/api/client.py
django_rebel/api/constants.py
django_rebel/api/mailgun.py
django_rebel/api/requesters.py
django_rebel/api/responses.py
django_rebel/migrations/0001_initial.py
django_rebel/migrations/0002_auto_20190114_0443.py
django_rebel/migrations/0003_auto_20200310_1740.py
django_rebel/migrations/0004_fill_events.py
django_rebel/migrations/0005_auto_20200314_1542.py
django_rebel/migrations/0006_alter_event_extra_data.py
django_rebel/migrations/__init__.py
tests/migrations/0001_initial.py
tests/migrations/__init__.py
tests/tests/__init__.py
tests/tests/test_mail_senders.py
tests/tests/test_prepared_mail.py
django_rebel-0.2.0.dist-info/LICENSE
django_rebel-0.2.0.dist-info/METADATA
django_rebel-0.2.0.dist-info/WHEEL
django_rebel-0.2.0.dist-info/top_level.txt
django_rebel-0.2.0.dist-info/RECORD
