Metadata-Version: 2.1
Name: django-rebel
Version: 0.2.0
Summary: Mailgun Backend for Django
Home-page: https://gitlab.com/socivy/django-rebel
Author: Socivy Developers
Author-email: info@socivy.com
License: MIT
Keywords: mail mailgun django
Platform: UNKNOWN
Classifier: Development Status :: 5 - Production/Stable
Classifier: Intended Audience :: Developers
Classifier: Topic :: Software Development :: Build Tools
Classifier: Programming Language :: Python :: 3
Classifier: Programming Language :: Python :: 3.3
Classifier: Programming Language :: Python :: 3.4
Classifier: Programming Language :: Python :: 3.5
Classifier: Programming Language :: Python :: 3.6
Classifier: Programming Language :: Python :: 3.7
Classifier: Programming Language :: Python :: 3.8
Requires-Dist: django (<3.3,>=3.0)
Requires-Dist: requests (<=3.0,>=2.0)
Requires-Dist: premailer (==3.2.0)
Provides-Extra: test
Requires-Dist: django (<3.3,>=3.0) ; extra == 'test'
Requires-Dist: requests (<=3.0,>=2.0) ; extra == 'test'
Requires-Dist: premailer (==3.2.0) ; extra == 'test'
